Metadata-Version: 2.1
Name: PyPackIT-Test1-TestSuite
Version: 0.0.10
Summary: A New Python Project
Author-email: Armin Ariamajd <armiariam@gmail.com>
Maintainer-email: Armin Ariamajd <armiariam@gmail.com>
License: MIT
Project-URL: Homepage, https://AAriam.github.io/PyPackIT-Test1
Project-URL: Source, https://github.com/AAriam/PyPackIT-Test1
Project-URL: Download, https://github.com/AAriam/PyPackIT-Test1/releases
Project-URL: Issue-Tracker, https://github.com/AAriam/PyPackIT-Test1/issues
Keywords: First Keyword,Second Keyword,Third Keyword,Fourth Keyword,Fifth Keyword,Sixth Keyword
Requires-Python: >=3.10
License-File: LICENSES/LICENSE-MIT
Requires-Dist: pytest==8.3.3
Requires-Dist: coverage==7.6.1
Requires-Dist: pytest-cov==5.0.0
Requires-Dist: pytest-html==4.1.1
Requires-Dist: pkgdata
